{"version": "1", "message": "ERROR: Hidden Testcases server unreachable.", "problem_id": "ads2_m10_a1_1", "user_id": "Surya", "score": {"sample": {"0": {"execution_time": 0.8573598861694336, "passed": true}, "1": {"execution_time": 0.8076121807098389, "passed": true}, "2": {"execution_time": 0.6820886135101318, "passed": true}, "3": {"execution_time": 0.24834036827087402, "passed": false}, "4": {"execution_time": 0.720961332321167, "passed": false}, "5": {"execution_time": 0.6376698017120361, "passed": false}, "6": {"execution_time": 0.6836190223693848, "passed": false}, "7": {"execution_time": 0.6447277069091797, "passed": false}, "8": {"execution_time": 0.6575908660888672, "passed": false}}}, "check_style_score": "0/1"}